<PAMDataset>
  <Metadata>
    <MDI key="DataType">Generic</MDI>
  </Metadata>
  <PAMRasterBand band="1">
    <Description>R</Description>
    <Histograms>
      <HistItem>
        <HistMin>-0.5</HistMin>
        <HistMax>207.5</HistMax>
        <BucketCount>208</BucketCount>
        <IncludeOutOfRange>1</IncludeOutOfRange>
        <Approximate>0</Approximate>
        <HistCounts>0|0|0|0|0|0|0|0|0|0|0|0|0|0|0|0|0|0|0|0|0|0|0|0|0|0|0|0|0|0|0|0|0|0|0|0|0|0|0|1|0|1|1|0|1|3|5|4|2|6|7|6|9|9|31|60|109|229|432|574|795|876|825|696|710|519|476|380|365|358|306|346|270|306|338|333|344|419|459|503|461|518|518|443|449|461|390|336|330|309|304|317|310|309|345|363|357|398|405|417|449|522|583|632|771|878|1146|1258|1620|1806|1966|1680|1601|1355|1280|1262|1303|1283|1313|1399|1299|1237|996|853|845|825|826|734|612|459|332|271|199|170|150|160|97|114|104|121|105|121|149|109|123|111|144|134|132|166|132|143|158|200|213|223|212|247|253|312|430|556|607|715|850|946|984|1091|1133|1209|1182|1186|1230|1208|1230|1223|1100|1020|949|896|683|767|987|954|1080|1198|1114|1140|1068|1173|1129|897|526|239|86|79|64|74|69|58|76|68|71|71|57|44|28|3</HistCounts>
      </HistItem>
    </Histograms>
    <Metadata>
      <MDI key="BandName">R</MDI>
      <MDI key="RepresentationType">ATHEMATIC</MDI>
      <MDI key="STATISTICS_COVARIANCES">1638.668844976297,1379.338081543007,1141.66084682837</MDI>
      <MDI key="STATISTICS_EXCLUDEDVALUES"></MDI>
      <MDI key="STATISTICS_MAXIMUM">207</MDI>
      <MDI key="STATISTICS_MEAN">131.3511406423</MDI>
      <MDI key="STATISTICS_MEDIAN">121.000000</MDI>
      <MDI key="STATISTICS_MINIMUM">39</MDI>
      <MDI key="STATISTICS_SKIPFACTORX">1</MDI>
      <MDI key="STATISTICS_SKIPFACTORY">1</MDI>
      <MDI key="STATISTICS_STDDEV">40.480474861052</MDI>
    </Metadata>
  </PAMRasterBand>
  <PAMRasterBand band="2">
    <Description>G</Description>
    <Histograms>
      <HistItem>
        <HistMin>-0.5</HistMin>
        <HistMax>204.5</HistMax>
        <BucketCount>205</BucketCount>
        <IncludeOutOfRange>1</IncludeOutOfRange>
        <Approximate>0</Approximate>
        <HistCounts>0|0|0|0|0|0|0|0|0|0|0|0|0|0|0|0|0|0|0|0|0|0|0|0|0|0|0|0|0|0|0|0|0|0|0|0|0|0|0|0|0|0|0|0|0|0|0|1|1|2|0|0|6|4|4|6|1|6|4|14|9|11|18|41|89|147|269|514|750|893|859|829|703|654|595|540|503|438|439|422|414|476|511|543|538|434|452|389|359|310|396|399|355|377|336|291|242|271|260|297|362|366|420|597|692|865|805|914|872|702|737|904|1071|1627|1801|1856|1701|1502|1213|1037|1004|1135|1273|1131|967|878|805|696|513|353|319|265|172|164|166|155|136|160|208|235|259|328|388|571|692|831|939|977|1040|985|879|830|834|795|734|671|632|731|752|846|870|964|1129|1286|1267|1147|1303|1182|1220|1093|1108|1066|861|754|919|886|803|966|985|933|929|889|935|1057|1001|945|568|322|125|52|66|69|59|74|67|63|43|69|61|80|47|54|40|24|4</HistCounts>
      </HistItem>
    </Histograms>
    <Metadata>
      <MDI key="BandName">G</MDI>
      <MDI key="RepresentationType">ATHEMATIC</MDI>
      <MDI key="STATISTICS_COVARIANCES">1379.338081543007,1239.373070626327,1025.793130483573</MDI>
      <MDI key="STATISTICS_EXCLUDEDVALUES"></MDI>
      <MDI key="STATISTICS_MAXIMUM">204</MDI>
      <MDI key="STATISTICS_MEAN">133.09053156146</MDI>
      <MDI key="STATISTICS_MEDIAN">129.000000</MDI>
      <MDI key="STATISTICS_MINIMUM">47</MDI>
      <MDI key="STATISTICS_SKIPFACTORX">1</MDI>
      <MDI key="STATISTICS_SKIPFACTORY">1</MDI>
      <MDI key="STATISTICS_STDDEV">35.204730798947</MDI>
    </Metadata>
  </PAMRasterBand>
  <PAMRasterBand band="3">
    <Description>B</Description>
    <Histograms>
      <HistItem>
        <HistMin>-0.5</HistMin>
        <HistMax>207.5</HistMax>
        <BucketCount>208</BucketCount>
        <IncludeOutOfRange>1</IncludeOutOfRange>
        <Approximate>0</Approximate>
        <HistCounts>0|0|0|0|0|0|0|0|0|0|0|0|0|0|0|0|0|0|0|0|0|0|0|0|0|0|0|0|0|0|0|0|0|0|0|0|0|0|0|0|0|0|0|0|0|0|0|0|0|0|0|0|0|1|2|1|5|4|7|14|14|20|23|29|47|54|71|115|150|163|164|172|173|214|197|235|223|223|246|308|453|703|905|1044|964|800|677|527|400|391|395|467|493|569|508|500|348|282|286|276|285|287|376|372|471|391|357|343|356|473|665|749|885|867|916|838|752|735|770|831|945|1475|2068|2200|1880|1502|1269|983|968|1048|1365|1632|1746|1433|1141|846|638|583|533|668|812|875|928|1015|860|839|847|808|801|740|665|659|703|752|798|994|1080|1245|1378|1292|1160|1053|950|1005|1071|1037|978|978|960|816|741|788|814|777|742|747|702|681|712|769|916|764|547|471|273|164|91|56|77|65|49|51|47|30|53|40|61|51|32|59|69|61|74|48|46|19|7|2</HistCounts>
      </HistItem>
    </Histograms>
    <Metadata>
      <MDI key="BandName">B</MDI>
      <MDI key="RepresentationType">ATHEMATIC</MDI>
      <MDI key="STATISTICS_COVARIANCES">1141.66084682837,1025.793130483573,892.9415119888878</MDI>
      <MDI key="STATISTICS_EXCLUDEDVALUES"></MDI>
      <MDI key="STATISTICS_MAXIMUM">207</MDI>
      <MDI key="STATISTICS_MEAN">134.18875968992</MDI>
      <MDI key="STATISTICS_MEDIAN">133.000000</MDI>
      <MDI key="STATISTICS_MINIMUM">53</MDI>
      <MDI key="STATISTICS_SKIPFACTORX">1</MDI>
      <MDI key="STATISTICS_SKIPFACTORY">1</MDI>
      <MDI key="STATISTICS_STDDEV">29.882126965611</MDI>
    </Metadata>
  </PAMRasterBand>
</PAMDataset>
