<PAMDataset>
  <Metadata>
    <MDI key="DataType">Generic</MDI>
  </Metadata>
  <PAMRasterBand band="1">
    <Description>R</Description>
    <Histograms>
      <HistItem>
        <HistMin>-0.5</HistMin>
        <HistMax>227.5</HistMax>
        <BucketCount>228</BucketCount>
        <IncludeOutOfRange>1</IncludeOutOfRange>
        <Approximate>0</Approximate>
        <HistCounts>0|0|0|0|0|0|0|0|0|0|0|0|0|5|18|19|25|40|50|151|319|273|234|203|162|182|201|258|243|247|290|283|286|353|321|342|347|384|385|429|432|462|471|514|482|462|485|502|520|496|520|515|540|530|469|511|460|456|411|424|447|421|433|452|484|507|561|544|572|528|550|468|421|427|370|425|421|374|417|371|331|330|351|389|363|363|303|383|368|360|380|381|351|364|416|363|382|409|430|421|402|462|442|463|491|547|500|481|480|437|507|547|573|633|651|706|768|829|807|851|802|799|765|898|952|995|1095|1043|1015|1094|1223|1087|1145|988|936|738|739|744|611|595|508|494|469|464|436|364|372|348|303|315|253|247|264|258|224|249|250|255|279|218|258|259|274|256|237|278|222|254|258|276|266|296|259|318|317|394|537|709|731|905|1036|914|754|536|379|275|258|232|212|244|246|251|234|222|237|218|239|283|275|346|320|435|494|632|567|524|403|296|223|138|73|55|56|38|37|30|31|21|15|9|11|15|6|8|6|4|2|2</HistCounts>
      </HistItem>
    </Histograms>
    <Metadata>
      <MDI key="BandName">R</MDI>
      <MDI key="RepresentationType">ATHEMATIC</MDI>
      <MDI key="STATISTICS_COVARIANCES">2514.218846115541,2027.101748270887,2147.128052058027</MDI>
      <MDI key="STATISTICS_EXCLUDEDVALUES"></MDI>
      <MDI key="STATISTICS_MAXIMUM">227</MDI>
      <MDI key="STATISTICS_MEAN">115.18726962457</MDI>
      <MDI key="STATISTICS_MEDIAN">120.000000</MDI>
      <MDI key="STATISTICS_MINIMUM">13</MDI>
      <MDI key="STATISTICS_SKIPFACTORX">1</MDI>
      <MDI key="STATISTICS_SKIPFACTORY">1</MDI>
      <MDI key="STATISTICS_STDDEV">50.141986858476</MDI>
    </Metadata>
  </PAMRasterBand>
  <PAMRasterBand band="2">
    <Description>G</Description>
    <Histograms>
      <HistItem>
        <HistMin>-0.5</HistMin>
        <HistMax>225.5</HistMax>
        <BucketCount>226</BucketCount>
        <IncludeOutOfRange>1</IncludeOutOfRange>
        <Approximate>0</Approximate>
        <HistCounts>0|0|0|0|0|0|0|0|0|0|0|0|0|0|0|0|0|0|0|0|0|0|0|1|4|16|18|15|14|23|53|229|342|280|166|121|104|120|164|147|155|145|139|162|181|196|159|222|204|186|233|193|217|277|242|297|243|295|278|285|326|302|311|305|319|335|417|422|411|481|565|470|574|584|676|639|657|860|851|898|858|791|833|690|661|704|688|663|638|663|650|667|625|662|657|639|639|686|675|715|677|704|741|749|801|812|765|808|840|913|962|1030|970|985|1007|992|957|1046|1060|1250|1299|1272|1317|1348|1374|1249|1110|901|823|763|670|640|535|546|491|444|456|445|422|355|347|352|321|280|257|266|292|240|244|218|234|211|226|242|291|220|255|235|246|230|259|280|270|253|249|236|236|267|220|270|243|278|288|338|425|579|721|869|961|880|786|559|407|290|263|237|215|216|237|213|223|215|231|250|247|254|287|364|383|470|587|622|543|422|336|205|152|92|67|69|46|24|48|39|22|24|19|14|7|6|5|2|8|1|0|2</HistCounts>
      </HistItem>
    </Histograms>
    <Metadata>
      <MDI key="BandName">G</MDI>
      <MDI key="RepresentationType">ATHEMATIC</MDI>
      <MDI key="STATISTICS_COVARIANCES">2027.101748270887,1783.582619280638,1836.751423324168</MDI>
      <MDI key="STATISTICS_EXCLUDEDVALUES"></MDI>
      <MDI key="STATISTICS_MAXIMUM">225</MDI>
      <MDI key="STATISTICS_MEAN">118.28129692833</MDI>
      <MDI key="STATISTICS_MEDIAN">115.000000</MDI>
      <MDI key="STATISTICS_MINIMUM">23</MDI>
      <MDI key="STATISTICS_SKIPFACTORX">1</MDI>
      <MDI key="STATISTICS_SKIPFACTORY">1</MDI>
      <MDI key="STATISTICS_STDDEV">42.232482987395</MDI>
    </Metadata>
  </PAMRasterBand>
  <PAMRasterBand band="3">
    <Description>B</Description>
    <Histograms>
      <HistItem>
        <HistMin>-0.5</HistMin>
        <HistMax>227.5</HistMax>
        <BucketCount>228</BucketCount>
        <IncludeOutOfRange>1</IncludeOutOfRange>
        <Approximate>0</Approximate>
        <HistCounts>0|0|0|0|0|0|0|0|0|0|0|0|0|0|0|0|0|0|0|0|0|0|0|0|0|0|0|0|0|0|0|0|0|0|0|0|10|31|58|95|345|469|251|177|167|181|184|207|236|244|345|342|387|405|546|534|546|606|728|766|736|770|794|813|830|727|662|643|588|583|513|483|469|442|432|467|444|418|453|413|411|411|418|412|429|405|396|446|423|486|528|567|658|707|701|645|668|596|592|494|552|530|570|599|643|668|662|680|700|606|723|742|832|860|926|977|1107|1240|1246|1300|1384|1358|1290|1351|1264|1118|1076|944|784|676|636|601|635|611|593|494|478|461|449|366|366|398|353|318|307|314|315|296|247|255|245|256|261|268|279|247|241|248|254|285|257|245|251|231|218|228|232|228|226|209|207|223|217|258|257|253|209|241|252|265|334|431|520|636|741|747|920|964|766|505|337|327|289|251|223|263|234|242|250|272|263|304|287|333|404|509|650|634|515|393|280|172|131|115|98|71|83|75|53|41|33|24|20|14|5|15|0|1</HistCounts>
      </HistItem>
    </Histograms>
    <Metadata>
      <MDI key="BandName">B</MDI>
      <MDI key="RepresentationType">ATHEMATIC</MDI>
      <MDI key="STATISTICS_COVARIANCES">2147.128052058027,1836.751423324168,2082.837251918892</MDI>
      <MDI key="STATISTICS_EXCLUDEDVALUES"></MDI>
      <MDI key="STATISTICS_MAXIMUM">227</MDI>
      <MDI key="STATISTICS_MEAN">120.32211604095</MDI>
      <MDI key="STATISTICS_MEDIAN">118.000000</MDI>
      <MDI key="STATISTICS_MINIMUM">36</MDI>
      <MDI key="STATISTICS_SKIPFACTORX">1</MDI>
      <MDI key="STATISTICS_SKIPFACTORY">1</MDI>
      <MDI key="STATISTICS_STDDEV">45.638111835602</MDI>
    </Metadata>
  </PAMRasterBand>
</PAMDataset>
