<PAMDataset>
  <Metadata>
    <MDI key="DataType">Generic</MDI>
  </Metadata>
  <PAMRasterBand band="1">
    <Histograms>
      <HistItem>
        <HistMin>-0.5</HistMin>
        <HistMax>231.5</HistMax>
        <BucketCount>232</BucketCount>
        <IncludeOutOfRange>1</IncludeOutOfRange>
        <Approximate>0</Approximate>
        <HistCounts>0|0|0|0|0|0|0|0|0|0|0|0|0|0|0|0|0|0|0|0|0|0|0|0|0|0|0|2|1|7|77|164|160|251|254|208|205|180|181|162|149|147|147|140|123|120|163|171|153|143|180|197|200|225|181|232|238|268|465|718|918|1545|1435|1416|1059|855|715|520|499|388|397|295|262|243|231|253|173|244|232|252|174|235|221|194|243|195|246|241|224|280|297|272|249|240|307|256|258|283|291|287|264|369|325|353|351|324|314|273|258|236|256|233|283|235|208|205|195|147|150|155|144|145|123|112|131|149|132|175|125|121|151|122|128|150|166|138|115|141|166|174|165|172|215|180|157|186|185|199|253|203|182|175|198|211|196|186|204|249|229|247|267|227|279|276|304|282|263|263|263|298|235|301|263|318|266|275|253|222|231|223|197|232|213|216|222|181|166|189|170|157|125|121|116|99|101|85|78|80|68|53|48|72|56|53|61|60|62|47|49|44|52|50|40|48|26|30|15|4|3|4|3|5|5|1|0|5|1|1|1|4|0|1</HistCounts>
      </HistItem>
    </Histograms>
    <Metadata>
      <MDI key="RepresentationType">ATHEMATIC</MDI>
      <MDI key="STATISTICS_COVARIANCES">2320.743723621938,1901.658205995898,1714.906994859916</MDI>
      <MDI key="STATISTICS_EXCLUDEDVALUES"></MDI>
      <MDI key="STATISTICS_MAXIMUM">231</MDI>
      <MDI key="STATISTICS_MEAN">105.60274376417</MDI>
      <MDI key="STATISTICS_MEDIAN">96.000000</MDI>
      <MDI key="STATISTICS_MINIMUM">27</MDI>
      <MDI key="STATISTICS_SKIPFACTORX">1</MDI>
      <MDI key="STATISTICS_SKIPFACTORY">1</MDI>
      <MDI key="STATISTICS_STDDEV">48.174098057171</MDI>
    </Metadata>
  </PAMRasterBand>
  <PAMRasterBand band="2">
    <Histograms>
      <HistItem>
        <HistMin>-0.5</HistMin>
        <HistMax>230.5</HistMax>
        <BucketCount>231</BucketCount>
        <IncludeOutOfRange>1</IncludeOutOfRange>
        <Approximate>0</Approximate>
        <HistCounts>0|0|0|0|0|0|0|0|0|0|0|0|0|0|0|0|0|0|0|0|0|0|0|0|0|0|0|0|0|0|0|0|0|0|0|0|0|4|0|10|10|18|21|17|22|52|70|73|102|88|99|133|138|196|183|223|205|142|110|178|110|133|118|169|120|179|180|263|472|855|1297|1646|1688|1327|975|739|562|502|424|368|338|246|225|267|246|243|244|241|233|237|292|306|277|293|306|318|318|385|388|363|431|406|368|361|403|380|467|508|477|445|436|368|390|374|364|328|271|273|215|253|228|195|207|246|223|218|205|233|192|209|243|199|195|229|216|216|270|257|209|243|240|248|234|275|249|232|235|249|222|226|264|252|280|275|337|270|224|268|240|215|238|238|194|247|235|230|217|218|181|188|182|191|201|221|199|238|198|220|204|205|187|198|155|166|169|136|130|105|107|106|126|106|83|71|65|60|59|63|46|60|49|64|60|54|48|46|45|40|45|39|43|41|30|26|18|4|3|7|0|4|2|5|1|4|0|1|1|0|2|1|1</HistCounts>
      </HistItem>
    </Histograms>
    <Metadata>
      <MDI key="RepresentationType">ATHEMATIC</MDI>
      <MDI key="STATISTICS_COVARIANCES">1901.658205995898,1633.528945146564,1466.202484576682</MDI>
      <MDI key="STATISTICS_EXCLUDEDVALUES"></MDI>
      <MDI key="STATISTICS_MAXIMUM">230</MDI>
      <MDI key="STATISTICS_MEAN">111.4989569161</MDI>
      <MDI key="STATISTICS_MEDIAN">105.000000</MDI>
      <MDI key="STATISTICS_MINIMUM">37</MDI>
      <MDI key="STATISTICS_SKIPFACTORX">1</MDI>
      <MDI key="STATISTICS_SKIPFACTORY">1</MDI>
      <MDI key="STATISTICS_STDDEV">40.416938839385</MDI>
    </Metadata>
  </PAMRasterBand>
  <PAMRasterBand band="3">
    <Histograms>
      <HistItem>
        <HistMin>-0.5</HistMin>
        <HistMax>232.5</HistMax>
        <BucketCount>233</BucketCount>
        <IncludeOutOfRange>1</IncludeOutOfRange>
        <Approximate>0</Approximate>
        <HistCounts>0|0|0|0|0|0|0|0|0|0|0|0|0|0|0|0|0|0|0|0|0|0|0|0|0|0|0|0|0|0|0|0|0|0|0|0|0|0|0|0|0|0|0|0|0|0|0|1|8|8|5|9|26|16|39|44|99|99|128|152|183|277|241|259|239|233|252|259|233|263|214|266|212|223|205|212|242|199|199|192|283|472|967|1279|1661|1530|1188|968|703|525|474|423|286|243|228|260|240|245|258|223|247|217|272|264|277|237|356|373|360|396|457|449|465|462|523|526|488|460|485|440|483|527|466|375|320|332|276|285|288|287|256|249|294|273|293|275|312|301|302|315|287|316|319|292|312|339|303|298|303|291|277|266|235|243|197|228|243|208|186|173|168|153|140|125|146|146|169|143|159|131|145|202|207|201|170|185|193|181|167|213|193|193|193|199|160|147|136|134|112|134|88|83|116|105|85|101|89|103|75|75|66|66|79|37|40|62|64|45|55|34|66|38|43|41|34|37|27|36|26|17|13|6|4|9|1|1|0|3|3|1|2|3|4</HistCounts>
      </HistItem>
    </Histograms>
    <Metadata>
      <MDI key="RepresentationType">ATHEMATIC</MDI>
      <MDI key="STATISTICS_COVARIANCES">1714.906994859916,1466.202484576682,1408.759008719255</MDI>
      <MDI key="STATISTICS_EXCLUDEDVALUES"></MDI>
      <MDI key="STATISTICS_MAXIMUM">232</MDI>
      <MDI key="STATISTICS_MEAN">117.12755102041</MDI>
      <MDI key="STATISTICS_MEDIAN">112.000000</MDI>
      <MDI key="STATISTICS_MINIMUM">47</MDI>
      <MDI key="STATISTICS_SKIPFACTORX">1</MDI>
      <MDI key="STATISTICS_SKIPFACTORY">1</MDI>
      <MDI key="STATISTICS_STDDEV">37.53343854111</MDI>
    </Metadata>
  </PAMRasterBand>
</PAMDataset>
