<PAMDataset>
  <Metadata>
    <MDI key="DataType">Generic</MDI>
  </Metadata>
  <PAMRasterBand band="1">
    <Description>R</Description>
    <Histograms>
      <HistItem>
        <HistMin>-0.5</HistMin>
        <HistMax>232.5</HistMax>
        <BucketCount>233</BucketCount>
        <IncludeOutOfRange>1</IncludeOutOfRange>
        <Approximate>0</Approximate>
        <HistCounts>0|0|0|0|0|0|0|0|0|0|0|0|0|0|0|0|0|0|0|0|0|1|9|40|112|135|155|194|231|208|202|245|235|227|293|329|308|351|401|395|470|447|558|572|565|646|541|580|575|605|543|528|547|593|452|505|506|470|499|497|478|421|487|377|498|428|470|397|433|385|414|403|346|380|316|362|324|401|360|386|358|393|350|377|386|307|441|414|375|411|427|437|502|578|645|837|928|1035|1176|1347|1535|1652|1473|1629|1410|1293|1198|1007|971|783|806|623|649|595|602|547|571|607|561|483|391|490|422|520|551|526|511|462|472|483|493|517|489|503|515|554|528|547|481|582|647|621|530|559|496|541|565|529|518|523|474|464|504|500|489|482|459|459|551|540|595|678|694|753|622|607|550|562|538|546|530|506|604|454|477|510|533|535|435|421|312|270|328|258|205|227|190|188|188|151|150|143|149|150|144|116|150|94|95|76|65|75|58|49|40|59|75|53|64|83|73|60|45|48|31|79|121|55|9|6|7|5|11|4|7|3|2|7|7|2|10|1|9</HistCounts>
      </HistItem>
    </Histograms>
    <Metadata>
      <MDI key="BandName">R</MDI>
      <MDI key="RepresentationType">ATHEMATIC</MDI>
      <MDI key="STATISTICS_COVARIANCES">1956.347208503656,1548.582930447604,1619.523795641075</MDI>
      <MDI key="STATISTICS_EXCLUDEDVALUES"></MDI>
      <MDI key="STATISTICS_MAXIMUM">232</MDI>
      <MDI key="STATISTICS_MEAN">111.16985555556</MDI>
      <MDI key="STATISTICS_MEDIAN">107.000000</MDI>
      <MDI key="STATISTICS_MINIMUM">21</MDI>
      <MDI key="STATISTICS_SKIPFACTORX">1</MDI>
      <MDI key="STATISTICS_SKIPFACTORY">1</MDI>
      <MDI key="STATISTICS_STDDEV">44.230613928632</MDI>
    </Metadata>
  </PAMRasterBand>
  <PAMRasterBand band="2">
    <Description>G</Description>
    <Histograms>
      <HistItem>
        <HistMin>-0.5</HistMin>
        <HistMax>226.5</HistMax>
        <BucketCount>227</BucketCount>
        <IncludeOutOfRange>1</IncludeOutOfRange>
        <Approximate>0</Approximate>
        <HistCounts>0|0|0|0|0|0|0|0|0|0|0|0|0|0|0|0|0|0|0|0|0|0|0|0|0|0|0|0|0|0|0|0|0|11|76|106|104|119|137|148|154|151|164|168|178|183|165|211|201|195|234|233|236|258|271|286|316|329|330|357|354|388|389|511|509|500|490|563|596|655|631|682|685|616|678|662|619|622|598|559|608|534|552|646|621|586|683|694|726|682|746|716|697|648|632|643|678|648|730|886|1028|1304|1489|1693|2049|2323|2341|1986|1931|1645|1376|1170|1020|1025|906|828|871|979|903|820|832|829|815|800|675|617|583|556|608|543|472|467|434|413|394|361|330|330|347|320|316|325|367|353|366|394|372|355|394|404|430|426|502|511|460|510|487|471|504|545|631|662|623|700|748|629|560|431|373|390|386|405|387|392|398|391|366|396|294|275|219|246|279|185|159|111|150|111|141|100|125|112|117|109|83|65|66|52|69|57|64|60|58|65|50|75|65|73|80|63|55|46|50|93|98|44|8|8|6|10|10|6|2|4|7|5|13</HistCounts>
      </HistItem>
    </Histograms>
    <Metadata>
      <MDI key="BandName">G</MDI>
      <MDI key="RepresentationType">ATHEMATIC</MDI>
      <MDI key="STATISTICS_COVARIANCES">1548.582930447604,1331.867682001885,1381.458078176422</MDI>
      <MDI key="STATISTICS_EXCLUDEDVALUES"></MDI>
      <MDI key="STATISTICS_MAXIMUM">226</MDI>
      <MDI key="STATISTICS_MEAN">113.28748888889</MDI>
      <MDI key="STATISTICS_MEDIAN">108.000000</MDI>
      <MDI key="STATISTICS_MINIMUM">33</MDI>
      <MDI key="STATISTICS_SKIPFACTORX">1</MDI>
      <MDI key="STATISTICS_SKIPFACTORY">1</MDI>
      <MDI key="STATISTICS_STDDEV">36.494762391361</MDI>
    </Metadata>
  </PAMRasterBand>
  <PAMRasterBand band="3">
    <Description>B</Description>
    <Histograms>
      <HistItem>
        <HistMin>-0.5</HistMin>
        <HistMax>229.5</HistMax>
        <BucketCount>230</BucketCount>
        <IncludeOutOfRange>1</IncludeOutOfRange>
        <Approximate>0</Approximate>
        <HistCounts>0|0|0|0|0|0|0|0|0|0|0|0|0|0|0|0|0|0|0|0|0|0|0|0|0|0|0|0|0|0|0|0|0|0|0|0|0|0|9|21|94|118|135|251|233|320|302|395|522|578|608|764|731|764|866|809|860|759|883|753|764|790|638|794|629|764|628|638|716|584|712|571|626|640|511|570|522|537|544|536|546|567|533|558|591|609|574|558|552|513|526|536|529|558|459|615|572|597|580|610|693|703|795|676|730|812|1016|1242|1512|1832|2157|2337|2616|2189|1982|1460|1382|1185|910|704|642|607|566|475|537|403|368|368|349|340|315|314|369|325|307|303|290|287|315|281|345|305|341|332|324|357|348|395|411|420|356|347|397|430|435|403|429|465|507|447|551|459|456|462|502|519|477|461|435|460|418|427|456|393|346|245|246|235|209|236|314|363|347|264|237|268|182|184|150|210|175|124|120|87|87|97|78|80|50|49|51|58|68|62|73|33|43|42|39|58|59|69|93|104|72|39|43|63|80|55|64|23|31|5|11|10|9|5|18|1</HistCounts>
      </HistItem>
    </Histograms>
    <Metadata>
      <MDI key="BandName">B</MDI>
      <MDI key="RepresentationType">ATHEMATIC</MDI>
      <MDI key="STATISTICS_COVARIANCES">1619.523795641075,1381.458078176422,1570.629852908337</MDI>
      <MDI key="STATISTICS_EXCLUDEDVALUES"></MDI>
      <MDI key="STATISTICS_MAXIMUM">229</MDI>
      <MDI key="STATISTICS_MEAN">109.5903</MDI>
      <MDI key="STATISTICS_MEDIAN">110.000000</MDI>
      <MDI key="STATISTICS_MINIMUM">38</MDI>
      <MDI key="STATISTICS_SKIPFACTORX">1</MDI>
      <MDI key="STATISTICS_SKIPFACTORY">1</MDI>
      <MDI key="STATISTICS_STDDEV">39.631172742026</MDI>
    </Metadata>
  </PAMRasterBand>
</PAMDataset>
