<PAMDataset>
  <Metadata>
    <MDI key="DataType">Generic</MDI>
  </Metadata>
  <PAMRasterBand band="1">
    <Description>R</Description>
    <Histograms>
      <HistItem>
        <HistMin>-0.5</HistMin>
        <HistMax>233.5</HistMax>
        <BucketCount>234</BucketCount>
        <IncludeOutOfRange>1</IncludeOutOfRange>
        <Approximate>0</Approximate>
        <HistCounts>0|0|0|0|0|0|0|0|0|0|0|0|0|0|0|0|0|0|0|5|15|42|91|72|128|145|155|172|237|302|301|329|375|393|307|356|372|379|413|401|390|418|353|347|358|379|374|403|361|335|369|379|328|349|307|307|307|297|338|263|256|273|253|279|235|282|209|236|234|199|289|257|348|342|432|338|338|278|353|315|346|451|425|465|556|525|614|626|702|748|770|804|755|706|689|767|690|565|642|751|625|604|568|514|458|514|509|644|703|712|768|759|846|872|883|778|774|725|738|713|753|694|658|627|572|463|430|472|461|462|456|458|474|500|439|463|451|405|403|432|470|496|504|521|529|481|485|492|514|521|583|645|724|751|789|734|733|748|757|837|805|791|850|787|859|944|903|927|848|883|861|845|854|1012|1082|1082|1100|899|915|972|1192|856|580|517|406|322|226|159|114|116|82|104|69|67|62|60|55|58|50|45|35|34|42|35|46|20|42|28|20|37|23|32|15|11|15|17|16|11|5|13|6|11|6|5|11|1|5|1|2|1|3|0|1|2</HistCounts>
      </HistItem>
    </Histograms>
    <Metadata>
      <MDI key="BandName">R</MDI>
      <MDI key="RepresentationType">ATHEMATIC</MDI>
      <MDI key="STATISTICS_COVARIANCES">2058.000697959756,1752.565937089972,1724.331445477736</MDI>
      <MDI key="STATISTICS_EXCLUDEDVALUES"></MDI>
      <MDI key="STATISTICS_MAXIMUM">233</MDI>
      <MDI key="STATISTICS_MEAN">120.2734662237</MDI>
      <MDI key="STATISTICS_MEDIAN">121.000000</MDI>
      <MDI key="STATISTICS_MINIMUM">19</MDI>
      <MDI key="STATISTICS_SKIPFACTORX">1</MDI>
      <MDI key="STATISTICS_SKIPFACTORY">1</MDI>
      <MDI key="STATISTICS_STDDEV">45.365192581535</MDI>
    </Metadata>
  </PAMRasterBand>
  <PAMRasterBand band="2">
    <Description>G</Description>
    <Histograms>
      <HistItem>
        <HistMin>-0.5</HistMin>
        <HistMax>228.5</HistMax>
        <BucketCount>229</BucketCount>
        <IncludeOutOfRange>1</IncludeOutOfRange>
        <Approximate>0</Approximate>
        <HistCounts>0|0|0|0|0|0|0|0|0|0|0|0|0|0|0|0|0|0|0|0|0|0|0|0|0|0|0|0|0|0|3|17|30|68|91|121|124|151|177|206|224|292|268|263|279|273|321|342|320|251|244|290|280|292|332|275|279|315|332|342|313|345|357|366|374|363|385|353|351|397|415|357|379|369|410|442|433|465|491|394|400|403|684|590|520|547|431|510|617|701|791|942|930|966|958|1026|1100|1037|864|958|946|805|769|770|745|770|830|840|921|884|1054|1037|1046|964|972|967|903|846|886|784|682|526|533|448|466|480|443|400|435|387|421|417|406|447|407|410|444|423|476|489|466|449|517|477|464|494|447|563|560|557|573|677|698|713|805|796|854|895|868|916|995|1005|997|1001|1026|956|940|864|852|793|802|819|775|856|793|815|859|742|604|651|845|902|465|230|163|116|100|98|65|70|51|48|42|52|48|28|30|25|38|34|39|41|39|53|24|27|31|31|29|28|13|13|16|24|8|10|9|12|10|6|10|11|1|3|5|3|3|0|2</HistCounts>
      </HistItem>
    </Histograms>
    <Metadata>
      <MDI key="BandName">G</MDI>
      <MDI key="RepresentationType">ATHEMATIC</MDI>
      <MDI key="STATISTICS_COVARIANCES">1752.565937089972,1591.235459889841,1570.294026081826</MDI>
      <MDI key="STATISTICS_EXCLUDEDVALUES"></MDI>
      <MDI key="STATISTICS_MAXIMUM">228</MDI>
      <MDI key="STATISTICS_MEAN">120.92222591362</MDI>
      <MDI key="STATISTICS_MEDIAN">117.000000</MDI>
      <MDI key="STATISTICS_MINIMUM">30</MDI>
      <MDI key="STATISTICS_SKIPFACTORX">1</MDI>
      <MDI key="STATISTICS_SKIPFACTORY">1</MDI>
      <MDI key="STATISTICS_STDDEV">39.890292802759</MDI>
    </Metadata>
  </PAMRasterBand>
  <PAMRasterBand band="3">
    <Description>B</Description>
    <Histograms>
      <HistItem>
        <HistMin>-0.5</HistMin>
        <HistMax>231.5</HistMax>
        <BucketCount>232</BucketCount>
        <IncludeOutOfRange>1</IncludeOutOfRange>
        <Approximate>0</Approximate>
        <HistCounts>0|0|0|0|0|0|0|0|0|0|0|0|0|0|0|0|0|0|0|0|0|0|0|0|0|0|0|0|0|0|0|0|0|0|0|1|1|11|20|40|72|97|134|142|231|262|392|444|521|500|590|511|577|523|648|523|592|594|484|513|425|478|363|420|427|377|376|320|398|315|360|381|367|331|321|327|384|435|472|517|513|443|428|467|598|634|595|509|473|472|498|630|547|596|557|582|577|718|838|894|1088|1183|1192|958|933|873|903|1128|1005|932|1025|990|1068|1031|829|844|851|789|774|681|696|582|674|659|593|550|538|502|496|421|467|418|456|403|459|417|418|454|391|439|444|461|458|436|484|402|406|517|493|574|591|637|669|754|766|819|878|890|920|934|921|928|976|989|1001|930|979|1020|881|865|818|791|650|534|492|355|414|362|400|429|520|456|476|600|592|470|429|417|468|502|196|53|49|44|37|42|43|36|30|33|43|39|32|35|38|37|45|36|22|32|27|35|39|33|14|7|13|11|16|13|16|8|16|15|6|1|4|3|1|1|3|2</HistCounts>
      </HistItem>
    </Histograms>
    <Metadata>
      <MDI key="BandName">B</MDI>
      <MDI key="RepresentationType">ATHEMATIC</MDI>
      <MDI key="STATISTICS_COVARIANCES">1724.331445477736,1570.294026081826,1656.550812831033</MDI>
      <MDI key="STATISTICS_EXCLUDEDVALUES"></MDI>
      <MDI key="STATISTICS_MAXIMUM">231</MDI>
      <MDI key="STATISTICS_MEAN">120.78317829457</MDI>
      <MDI key="STATISTICS_MEDIAN">117.000000</MDI>
      <MDI key="STATISTICS_MINIMUM">35</MDI>
      <MDI key="STATISTICS_SKIPFACTORX">1</MDI>
      <MDI key="STATISTICS_SKIPFACTORY">1</MDI>
      <MDI key="STATISTICS_STDDEV">40.70074707952</MDI>
    </Metadata>
  </PAMRasterBand>
</PAMDataset>
