<PAMDataset>
  <Metadata>
    <MDI key="DataType">Generic</MDI>
  </Metadata>
  <PAMRasterBand band="1">
    <Histograms>
      <HistItem>
        <HistMin>-0.5</HistMin>
        <HistMax>255.5</HistMax>
        <BucketCount>256</BucketCount>
        <IncludeOutOfRange>1</IncludeOutOfRange>
        <Approximate>0</Approximate>
        <HistCounts>6|31|67|151|320|628|1049|1570|2124|2498|2565|2711|2758|2951|3128|3171|3196|3311|3341|3424|3452|3582|3615|3598|3436|3280|2964|2696|2392|2147|1951|1757|1614|1452|1256|1175|1029|1010|1018|1027|1012|940|948|896|869|859|860|836|854|790|768|779|809|718|707|713|692|716|674|746|721|725|645|669|663|666|610|588|595|656|664|584|578|626|635|631|587|629|611|663|617|631|580|627|628|622|611|567|618|606|663|634|628|663|678|691|627|629|647|670|722|700|687|736|790|732|784|820|858|902|855|856|890|832|798|927|824|845|800|810|878|895|830|935|928|962|964|984|955|993|1007|987|980|1004|947|1022|946|936|943|934|860|858|846|841|775|810|845|855|819|837|783|865|768|807|781|779|803|797|827|778|815|774|834|914|878|931|988|997|1039|1118|1214|1243|1294|1309|1441|1306|1437|1375|1439|1443|1507|1474|1514|1518|1468|1552|1534|1450|1415|1373|1343|1286|1267|1237|1143|1109|1148|1038|985|1002|895|893|897|855|852|806|819|783|722|737|670|659|664|656|605|552|523|457|425|432|429|419|390|402|416|389|408|441|435|464|420|448|394|409|374|376|341|329|307|289|251|218|207|145|125|110|117|87|80|95|87|106|120|116|100|50</HistCounts>
      </HistItem>
    </Histograms>
    <Metadata>
      <MDI key="RepresentationType">ATHEMATIC</MDI>
      <MDI key="STATISTICS_COVARIANCES">5250.630023846219,4596.751092291034,3582.92091768845</MDI>
      <MDI key="STATISTICS_EXCLUDEDVALUES"></MDI>
      <MDI key="STATISTICS_MAXIMUM">255</MDI>
      <MDI key="STATISTICS_MEAN">101.24721843687</MDI>
      <MDI key="STATISTICS_MEDIAN">99.000000</MDI>
      <MDI key="STATISTICS_MINIMUM">0</MDI>
      <MDI key="STATISTICS_SKIPFACTORX">1</MDI>
      <MDI key="STATISTICS_SKIPFACTORY">1</MDI>
      <MDI key="STATISTICS_STDDEV">72.461231178101</MDI>
    </Metadata>
  </PAMRasterBand>
  <PAMRasterBand band="2">
    <Histograms>
      <HistItem>
        <HistMin>-0.5</HistMin>
        <HistMax>255.5</HistMax>
        <BucketCount>256</BucketCount>
        <IncludeOutOfRange>1</IncludeOutOfRange>
        <Approximate>0</Approximate>
        <HistCounts>1|1|5|8|15|29|48|91|115|159|222|335|394|537|655|782|948|1124|1241|1447|1601|1696|1820|2026|2313|2544|2792|2714|2988|3016|3146|3183|3266|3124|3205|3369|3543|3590|3661|3268|3074|2906|2584|2165|2006|1721|1512|1348|1269|1140|1079|1051|1069|988|1040|1041|986|1015|994|1019|897|945|896|955|919|913|874|854|866|844|812|838|825|808|767|727|737|742|731|749|728|720|765|702|693|743|717|762|769|712|657|684|759|724|690|752|732|767|747|773|768|771|770|782|773|757|818|872|836|882|924|878|941|928|970|946|1046|1037|1024|973|1018|1043|1007|1109|1146|1092|1114|1182|1256|1146|1097|1094|1139|1052|1078|1050|1042|992|1000|1062|963|1005|1043|983|964|996|998|986|898|957|946|978|964|936|1060|1121|1133|1234|1221|1250|1326|1376|1424|1438|1457|1469|1501|1465|1463|1508|1563|1524|1491|1484|1452|1484|1351|1340|1297|1279|1215|1193|1219|1118|1093|961|1019|994|891|885|862|775|840|794|838|793|755|717|704|641|685|570|584|563|545|514|559|504|479|445|417|408|384|379|401|360|326|310|313|296|342|359|409|403|429|376|401|433|363|332|290|301|269|227|249|187|163|168|140|104|91|111|87|99|76|96|82|77|61|57|67|70|62|49|35|19</HistCounts>
      </HistItem>
    </Histograms>
    <Metadata>
      <MDI key="RepresentationType">ATHEMATIC</MDI>
      <MDI key="STATISTICS_COVARIANCES">4596.751092291034,4088.207297953681,3229.833376549589</MDI>
      <MDI key="STATISTICS_EXCLUDEDVALUES"></MDI>
      <MDI key="STATISTICS_MAXIMUM">255</MDI>
      <MDI key="STATISTICS_MEAN">101.92114629258</MDI>
      <MDI key="STATISTICS_MEDIAN">97.000000</MDI>
      <MDI key="STATISTICS_MINIMUM">0</MDI>
      <MDI key="STATISTICS_SKIPFACTORX">1</MDI>
      <MDI key="STATISTICS_SKIPFACTORY">1</MDI>
      <MDI key="STATISTICS_STDDEV">63.939090531174</MDI>
    </Metadata>
  </PAMRasterBand>
  <PAMRasterBand band="3">
    <Histograms>
      <HistItem>
        <HistMin>-0.5</HistMin>
        <HistMax>255.5</HistMax>
        <BucketCount>256</BucketCount>
        <IncludeOutOfRange>1</IncludeOutOfRange>
        <Approximate>0</Approximate>
        <HistCounts>0|0|0|0|0|0|0|0|0|0|1|3|5|7|12|13|16|13|25|36|48|44|56|53|92|124|144|162|234|242|294|346|445|512|611|771|866|1015|1206|1212|1351|1536|1731|1982|2223|2374|2657|2766|2905|2962|3143|3075|3149|3234|3282|3259|3325|3335|3331|3470|3559|3527|3401|3297|3175|2780|2571|2296|2048|1884|1588|1543|1364|1413|1398|1291|1357|1273|1237|1238|1175|1188|1166|1088|1075|1062|1005|1043|986|966|937|958|989|907|913|954|998|931|926|934|927|894|883|922|925|960|966|930|973|977|1018|1124|1104|1200|1146|1240|1213|1227|1250|1263|1368|1348|1381|1404|1429|1331|1454|1329|1370|1349|1401|1378|1424|1406|1501|1377|1490|1389|1528|1520|1548|1718|1683|1638|1577|1646|1638|1611|1622|1522|1482|1605|1545|1513|1482|1497|1463|1455|1431|1356|1389|1319|1350|1210|1210|1190|1118|1103|1102|1028|1037|954|904|953|965|894|858|872|787|779|852|755|706|681|690|674|654|619|585|572|547|514|538|527|497|493|445|466|464|394|402|352|337|321|309|333|312|325|337|303|300|330|286|270|289|239|273|251|265|225|264|266|230|233|238|223|208|183|194|211|189|169|183|141|140|127|133|113|107|94|79|79|70|66|54|53|33|23|23|16|25|21|13|18|17|20</HistCounts>
      </HistItem>
    </Histograms>
    <Metadata>
      <MDI key="RepresentationType">ATHEMATIC</MDI>
      <MDI key="STATISTICS_COVARIANCES">3582.92091768845,3229.833376549589,2625.715895347087</MDI>
      <MDI key="STATISTICS_EXCLUDEDVALUES"></MDI>
      <MDI key="STATISTICS_MAXIMUM">255</MDI>
      <MDI key="STATISTICS_MEAN">105.53896593186</MDI>
      <MDI key="STATISTICS_MEDIAN">98.000000</MDI>
      <MDI key="STATISTICS_MINIMUM">10</MDI>
      <MDI key="STATISTICS_SKIPFACTORX">1</MDI>
      <MDI key="STATISTICS_SKIPFACTORY">1</MDI>
      <MDI key="STATISTICS_STDDEV">51.24173977674</MDI>
    </Metadata>
  </PAMRasterBand>
</PAMDataset>
