<PAMDataset>
  <Metadata>
    <MDI key="DataType">Generic</MDI>
  </Metadata>
  <PAMRasterBand band="1">
    <Histograms>
      <HistItem>
        <HistMin>-0.5</HistMin>
        <HistMax>250.5</HistMax>
        <BucketCount>251</BucketCount>
        <IncludeOutOfRange>1</IncludeOutOfRange>
        <Approximate>0</Approximate>
        <HistCounts>6|24|73|125|271|468|753|1086|1331|1367|1322|1324|1225|1186|1135|1007|937|897|876|845|802|848|723|803|775|760|735|689|681|666|716|691|692|716|702|744|795|841|837|852|868|962|914|973|1006|1078|1200|1308|1299|1367|1470|1379|1264|1289|1271|1266|1243|1247|1224|1336|1285|1371|1324|1271|1347|1490|1495|1504|1574|1545|1666|1557|1601|1545|1537|1408|1342|1428|1368|1343|1306|1344|1336|1421|1375|1408|1437|1470|1499|1416|1441|1465|1417|1407|1374|1378|1285|1297|1349|1324|1367|1263|1303|1406|1295|1220|1237|1248|1218|1126|1137|1122|1064|1116|1124|1128|1141|1170|1163|1189|1142|1204|1242|1189|1109|1070|1101|1063|1073|1028|1054|1043|1032|1028|1043|1131|1129|1095|1190|1165|1205|1157|1111|1129|1112|1134|1084|1068|1053|1100|1113|1155|1130|1117|1159|1145|1129|1212|1217|1236|1232|1309|1330|1351|1327|1373|1334|1402|1383|1486|1414|1415|1433|1447|1422|1474|1500|1420|1473|1581|1427|1436|1506|1403|1409|1326|1399|1306|1302|1242|1179|1166|1092|1112|1040|1026|991|921|916|953|848|750|768|786|788|804|763|806|800|885|861|807|697|572|464|365|309|255|255|233|205|251|256|236|209|212|221|184|185|171|203|170|183|126|139|117|81|76|63|52|31|29|11|18|6|6|5|1|4|0|1</HistCounts>
      </HistItem>
    </Histograms>
    <Metadata>
      <MDI key="RepresentationType">ATHEMATIC</MDI>
      <MDI key="STATISTICS_COVARIANCES">3490.383106257717,3154.054633056415,2745.301184690256</MDI>
      <MDI key="STATISTICS_EXCLUDEDVALUES"></MDI>
      <MDI key="STATISTICS_MAXIMUM">250</MDI>
      <MDI key="STATISTICS_MEAN">112.25534268537</MDI>
      <MDI key="STATISTICS_MEDIAN">110.000000</MDI>
      <MDI key="STATISTICS_MINIMUM">0</MDI>
      <MDI key="STATISTICS_SKIPFACTORX">1</MDI>
      <MDI key="STATISTICS_SKIPFACTORY">1</MDI>
      <MDI key="STATISTICS_STDDEV">59.079464336246</MDI>
    </Metadata>
  </PAMRasterBand>
  <PAMRasterBand band="2">
    <Histograms>
      <HistItem>
        <HistMin>-0.5</HistMin>
        <HistMax>249.5</HistMax>
        <BucketCount>250</BucketCount>
        <IncludeOutOfRange>1</IncludeOutOfRange>
        <Approximate>0</Approximate>
        <HistCounts>0|4|4|11|25|55|78|107|131|200|270|330|435|441|510|564|608|676|693|790|867|876|948|933|998|1051|1124|1138|1142|1023|1055|1006|981|969|968|905|887|862|887|927|923|960|1063|1044|1020|1138|1204|1195|1226|1285|1260|1365|1464|1517|1470|1497|1514|1532|1540|1597|1604|1635|1705|1705|1708|1693|1659|1615|1555|1504|1567|1546|1396|1538|1545|1598|1656|1722|1790|1756|1807|1771|1834|1673|1658|1686|1689|1682|1546|1625|1531|1520|1579|1587|1516|1577|1574|1528|1497|1508|1448|1457|1333|1374|1308|1323|1375|1437|1381|1456|1430|1476|1404|1314|1251|1300|1246|1241|1263|1175|1270|1088|1117|1140|1176|1174|1144|1183|1145|1198|1204|1182|1214|1201|1208|1123|1112|1179|1076|1075|1191|1146|1157|1168|1201|1242|1233|1255|1234|1247|1253|1331|1264|1334|1357|1384|1410|1405|1439|1417|1492|1529|1450|1444|1453|1498|1545|1568|1527|1567|1535|1512|1549|1508|1481|1457|1383|1373|1328|1259|1222|1144|1120|1071|1043|993|957|913|891|806|783|742|704|652|610|592|551|530|539|584|475|484|459|507|498|561|566|653|714|682|651|589|539|445|400|377|318|272|216|181|171|133|137|122|115|107|126|88|106|95|93|119|79|100|70|62|53|35|34|31|23|20|11|13|7|3|3|1|3|1</HistCounts>
      </HistItem>
    </Histograms>
    <Metadata>
      <MDI key="RepresentationType">ATHEMATIC</MDI>
      <MDI key="STATISTICS_COVARIANCES">3154.054633056415,2892.193994992504,2526.529937511142</MDI>
      <MDI key="STATISTICS_EXCLUDEDVALUES"></MDI>
      <MDI key="STATISTICS_MAXIMUM">249</MDI>
      <MDI key="STATISTICS_MEAN">109.96388376754</MDI>
      <MDI key="STATISTICS_MEDIAN">106.000000</MDI>
      <MDI key="STATISTICS_MINIMUM">1</MDI>
      <MDI key="STATISTICS_SKIPFACTORX">1</MDI>
      <MDI key="STATISTICS_SKIPFACTORY">1</MDI>
      <MDI key="STATISTICS_STDDEV">53.779122296599</MDI>
    </Metadata>
  </PAMRasterBand>
  <PAMRasterBand band="3">
    <Histograms>
      <HistItem>
        <HistMin>-0.5</HistMin>
        <HistMax>251.5</HistMax>
        <BucketCount>252</BucketCount>
        <IncludeOutOfRange>1</IncludeOutOfRange>
        <Approximate>0</Approximate>
        <HistCounts>0|0|0|0|0|0|0|1|1|1|0|1|1|6|3|9|9|12|17|16|20|40|50|70|96|147|174|225|269|329|415|531|594|728|901|1025|1196|1360|1447|1530|1592|1653|1663|1745|1652|1723|1689|1665|1707|1664|1687|1681|1781|1905|1880|1943|1976|2013|2075|2155|2196|2192|2346|2218|2250|2121|2185|2043|2002|1933|1947|1983|1965|1997|1995|2110|2120|2105|2065|2107|2068|2030|1994|1906|1847|1849|1718|1693|1774|1679|1728|1707|1714|1598|1656|1666|1680|1601|1660|1603|1530|1464|1527|1410|1538|1398|1366|1353|1357|1359|1302|1245|1280|1307|1291|1272|1361|1327|1337|1384|1336|1430|1393|1306|1382|1278|1329|1293|1317|1348|1379|1331|1383|1356|1349|1290|1335|1345|1323|1386|1366|1423|1395|1438|1412|1402|1526|1428|1493|1563|1557|1525|1507|1570|1643|1571|1636|1572|1634|1633|1556|1550|1480|1476|1373|1330|1274|1236|1215|1098|1098|1076|1043|989|915|887|836|794|775|792|744|693|611|570|567|485|487|504|449|467|419|428|393|368|367|380|354|384|385|421|392|411|434|456|488|540|526|530|434|454|406|348|318|264|243|199|179|146|137|110|89|85|86|68|70|73|62|57|70|73|55|69|69|80|59|69|58|52|66|42|31|26|25|19|13|10|10|7|5|1|0|2</HistCounts>
      </HistItem>
    </Histograms>
    <Metadata>
      <MDI key="RepresentationType">ATHEMATIC</MDI>
      <MDI key="STATISTICS_COVARIANCES">2745.301184690256,2526.529937511142,2267.87221896125</MDI>
      <MDI key="STATISTICS_EXCLUDEDVALUES"></MDI>
      <MDI key="STATISTICS_MAXIMUM">251</MDI>
      <MDI key="STATISTICS_MEAN">106.80755511022</MDI>
      <MDI key="STATISTICS_MEDIAN">100.000000</MDI>
      <MDI key="STATISTICS_MINIMUM">7</MDI>
      <MDI key="STATISTICS_SKIPFACTORX">1</MDI>
      <MDI key="STATISTICS_SKIPFACTORY">1</MDI>
      <MDI key="STATISTICS_STDDEV">47.622182005461</MDI>
    </Metadata>
  </PAMRasterBand>
</PAMDataset>
