<PAMDataset>
  <Metadata>
    <MDI key="DataType">Generic</MDI>
  </Metadata>
  <PAMRasterBand band="1">
    <Description>R</Description>
    <Histograms>
      <HistItem>
        <HistMin>-0.5</HistMin>
        <HistMax>235.5</HistMax>
        <BucketCount>236</BucketCount>
        <IncludeOutOfRange>1</IncludeOutOfRange>
        <Approximate>0</Approximate>
        <HistCounts>0|0|0|0|0|0|0|0|0|0|0|0|0|3|30|146|400|611|933|1167|1284|1359|1386|1483|1416|1541|1614|1555|1687|1870|1911|1946|2005|2143|2288|2189|2234|2313|2235|2190|2118|1913|1814|1756|1513|1448|1289|1218|1068|980|869|824|748|690|734|678|660|609|607|605|636|601|562|601|567|533|494|444|446|419|402|383|389|384|344|374|337|335|338|363|383|402|347|371|352|367|270|333|295|294|285|280|252|251|267|234|214|220|188|243|175|209|183|178|200|167|146|181|174|158|157|171|175|130|178|167|182|187|158|152|183|189|184|195|207|182|197|169|225|145|195|154|170|165|145|172|152|161|172|200|181|190|165|145|122|135|148|134|172|168|170|148|128|150|122|130|158|125|112|134|101|111|105|91|106|108|114|99|116|122|128|113|119|119|169|161|139|140|171|127|106|98|82|54|21|21|25|29|19|22|15|18|16|22|16|13|13|12|17|9|12|3|9|5|6|6|6|10|12|4|5|6|2|0|0|3|3|1|1|2|0|2|2|0|2|1|2|0|0|0|0|0|0|0|0|1</HistCounts>
      </HistItem>
    </Histograms>
    <Metadata>
      <MDI key="BandName">R</MDI>
      <MDI key="RepresentationType">ATHEMATIC</MDI>
      <MDI key="STATISTICS_COVARIANCES">1552.242038865983,1229.143385144288,1083.098337749288</MDI>
      <MDI key="STATISTICS_EXCLUDEDVALUES"></MDI>
      <MDI key="STATISTICS_MAXIMUM">235</MDI>
      <MDI key="STATISTICS_MEAN">57.5493</MDI>
      <MDI key="STATISTICS_MEDIAN">42.000000</MDI>
      <MDI key="STATISTICS_MINIMUM">13</MDI>
      <MDI key="STATISTICS_SKIPFACTORX">1</MDI>
      <MDI key="STATISTICS_SKIPFACTORY">1</MDI>
      <MDI key="STATISTICS_STDDEV">39.398503002855</MDI>
    </Metadata>
  </PAMRasterBand>
  <PAMRasterBand band="2">
    <Description>G</Description>
    <Histograms>
      <HistItem>
        <HistMin>-0.5</HistMin>
        <HistMax>227.5</HistMax>
        <BucketCount>228</BucketCount>
        <IncludeOutOfRange>1</IncludeOutOfRange>
        <Approximate>0</Approximate>
        <HistCounts>0|0|0|0|0|0|0|0|0|0|0|0|0|0|0|0|0|0|0|0|0|0|0|9|43|165|422|650|944|967|1120|1202|1299|1243|1349|1297|1398|1437|1538|1578|1604|1787|1891|1927|2082|2018|1938|2174|2166|2085|1931|1986|2008|1891|1658|1552|1438|1316|1213|1071|1006|933|791|813|772|734|689|675|707|655|717|772|756|654|652|670|561|625|536|526|506|494|522|538|502|548|580|620|608|631|583|565|534|529|490|445|475|443|374|389|371|399|395|359|362|335|317|326|334|285|349|249|296|293|260|251|264|244|248|306|227|203|186|189|205|200|220|220|174|150|139|128|103|97|108|119|93|129|110|104|73|64|81|75|68|60|76|59|53|64|69|74|65|59|70|83|69|95|74|83|82|93|103|79|106|94|121|136|103|114|111|127|114|108|104|67|52|52|35|35|18|21|19|15|19|19|11|33|19|18|13|13|17|16|9|10|6|12|2|7|5|9|3|3|9|6|7|9|9|3|1|1|4|4|3|1|0|2|1|3|0|0|3|0|0|0|1|2</HistCounts>
      </HistItem>
    </Histograms>
    <Metadata>
      <MDI key="BandName">G</MDI>
      <MDI key="RepresentationType">ATHEMATIC</MDI>
      <MDI key="STATISTICS_COVARIANCES">1229.143385144288,1055.963323940131,905.6914571934757</MDI>
      <MDI key="STATISTICS_EXCLUDEDVALUES"></MDI>
      <MDI key="STATISTICS_MAXIMUM">227</MDI>
      <MDI key="STATISTICS_MEAN">65.300311111111</MDI>
      <MDI key="STATISTICS_MEDIAN">54.000000</MDI>
      <MDI key="STATISTICS_MINIMUM">23</MDI>
      <MDI key="STATISTICS_SKIPFACTORX">1</MDI>
      <MDI key="STATISTICS_SKIPFACTORY">1</MDI>
      <MDI key="STATISTICS_STDDEV">32.495589299782</MDI>
    </Metadata>
  </PAMRasterBand>
  <PAMRasterBand band="3">
    <Description>B</Description>
    <Histograms>
      <HistItem>
        <HistMin>-0.5</HistMin>
        <HistMax>229.5</HistMax>
        <BucketCount>230</BucketCount>
        <IncludeOutOfRange>1</IncludeOutOfRange>
        <Approximate>0</Approximate>
        <HistCounts>0|0|0|0|0|0|0|0|0|0|0|0|0|0|0|0|0|0|0|0|0|0|0|0|0|0|0|0|0|0|2|27|240|597|1002|1566|1935|1970|2463|2846|2904|4004|4293|4952|5135|4323|3966|3256|2470|2248|1885|1493|1498|1231|1218|1036|995|892|860|899|759|832|718|758|738|702|671|608|596|527|503|502|460|483|463|467|453|373|352|380|376|418|396|373|389|405|387|359|340|333|319|298|375|443|457|523|367|340|309|301|238|252|217|191|199|214|231|258|191|252|250|207|187|184|179|162|205|161|168|142|127|162|135|127|102|90|92|86|79|86|81|89|59|64|54|66|74|75|63|45|64|67|63|56|59|67|55|53|73|44|66|61|48|74|62|83|82|94|73|82|69|84|106|93|86|91|75|97|96|85|90|81|56|47|40|30|30|18|16|22|24|29|18|21|22|18|18|12|16|19|12|15|15|14|5|11|16|13|6|6|6|6|11|6|4|12|9|10|8|8|14|4|4|8|9|7|5|1|1|1|4|2|2|0|0|1|0|3|0|3</HistCounts>
      </HistItem>
    </Histograms>
    <Metadata>
      <MDI key="BandName">B</MDI>
      <MDI key="RepresentationType">ATHEMATIC</MDI>
      <MDI key="STATISTICS_COVARIANCES">1083.098337749288,905.6914571934757,859.5063958279743</MDI>
      <MDI key="STATISTICS_EXCLUDEDVALUES"></MDI>
      <MDI key="STATISTICS_MAXIMUM">229</MDI>
      <MDI key="STATISTICS_MEAN">59.880144444444</MDI>
      <MDI key="STATISTICS_MEDIAN">47.000000</MDI>
      <MDI key="STATISTICS_MINIMUM">30</MDI>
      <MDI key="STATISTICS_SKIPFACTORX">1</MDI>
      <MDI key="STATISTICS_SKIPFACTORY">1</MDI>
      <MDI key="STATISTICS_STDDEV">29.317339508011</MDI>
    </Metadata>
  </PAMRasterBand>
</PAMDataset>
