<PAMDataset>
  <Metadata>
    <MDI key="DataType">Generic</MDI>
  </Metadata>
  <PAMRasterBand band="1">
    <Description>R</Description>
    <Histograms>
      <HistItem>
        <HistMin>-0.5</HistMin>
        <HistMax>235.5</HistMax>
        <BucketCount>236</BucketCount>
        <IncludeOutOfRange>1</IncludeOutOfRange>
        <Approximate>0</Approximate>
        <HistCounts>0|0|0|0|0|0|0|0|0|0|0|0|0|0|0|0|0|0|0|0|0|0|0|0|0|10|19|31|60|129|211|306|273|333|340|332|359|392|366|434|426|446|486|442|440|433|368|437|422|420|442|429|424|363|406|321|346|381|380|361|333|309|336|327|332|342|317|336|332|309|315|336|272|307|301|285|277|279|286|276|307|324|261|319|273|330|389|368|407|400|475|511|506|540|701|720|802|838|890|885|782|790|774|724|692|705|841|877|901|990|942|961|740|819|862|760|665|656|569|574|587|486|551|516|572|507|517|497|479|617|592|593|620|625|655|640|657|665|613|616|559|539|509|551|508|526|529|509|479|519|428|452|478|476|481|506|433|415|412|430|368|372|375|380|329|349|398|429|491|472|486|523|470|464|532|616|771|707|658|710|738|607|519|426|389|363|257|234|220|224|196|179|178|161|136|122|152|138|117|157|125|182|180|232|256|362|459|594|759|1022|988|740|519|383|332|337|274|584|1057|99|11|15|15|24|41|13|22|7|13|27|8|10|3|3|0|2</HistCounts>
      </HistItem>
    </Histograms>
    <Metadata>
      <MDI key="BandName">R</MDI>
      <MDI key="RepresentationType">ATHEMATIC</MDI>
      <MDI key="STATISTICS_COVARIANCES">2579.988070655848,2289.695784277033,2351.223959554112</MDI>
      <MDI key="STATISTICS_EXCLUDEDVALUES"></MDI>
      <MDI key="STATISTICS_MAXIMUM">235</MDI>
      <MDI key="STATISTICS_MEAN">125.41181616833</MDI>
      <MDI key="STATISTICS_MEDIAN">122.000000</MDI>
      <MDI key="STATISTICS_MINIMUM">25</MDI>
      <MDI key="STATISTICS_SKIPFACTORX">1</MDI>
      <MDI key="STATISTICS_SKIPFACTORY">1</MDI>
      <MDI key="STATISTICS_STDDEV">50.793582967299</MDI>
    </Metadata>
  </PAMRasterBand>
  <PAMRasterBand band="2">
    <Description>G</Description>
    <Histograms>
      <HistItem>
        <HistMin>-0.5</HistMin>
        <HistMax>233.5</HistMax>
        <BucketCount>234</BucketCount>
        <IncludeOutOfRange>1</IncludeOutOfRange>
        <Approximate>0</Approximate>
        <HistCounts>0|0|0|0|0|0|0|0|0|0|0|0|0|0|0|0|0|0|0|0|0|0|0|0|0|0|0|0|0|0|0|1|0|3|5|21|50|107|134|214|267|282|314|321|306|304|349|339|358|386|358|360|315|292|340|374|379|354|416|361|366|359|354|377|358|354|324|308|359|334|350|348|371|345|380|335|345|372|330|360|336|332|341|336|356|313|346|362|389|357|430|386|443|476|489|565|643|705|717|822|972|1085|1224|1197|1072|1039|1057|1127|1053|1188|1270|1211|1151|1106|1161|971|967|838|771|774|719|668|676|655|665|692|772|785|751|759|731|666|642|642|590|654|697|661|590|569|529|481|461|470|466|435|420|475|423|413|429|428|417|456|441|390|353|382|370|399|408|425|469|480|476|417|484|428|535|583|458|464|447|459|495|529|540|583|637|562|440|336|296|298|306|291|238|186|145|158|175|136|165|140|152|156|114|145|158|176|207|259|305|415|502|618|886|990|940|646|433|334|288|275|280|517|1057|136|16|30|13|14|21|17|5|7|7|10|23|8|7|4|0|1</HistCounts>
      </HistItem>
    </Histograms>
    <Metadata>
      <MDI key="BandName">G</MDI>
      <MDI key="RepresentationType">ATHEMATIC</MDI>
      <MDI key="STATISTICS_COVARIANCES">2289.695784277033,2097.240502340959,2128.48113541406</MDI>
      <MDI key="STATISTICS_EXCLUDEDVALUES"></MDI>
      <MDI key="STATISTICS_MAXIMUM">233</MDI>
      <MDI key="STATISTICS_MEAN">126.76436323367</MDI>
      <MDI key="STATISTICS_MEDIAN">120.000000</MDI>
      <MDI key="STATISTICS_MINIMUM">31</MDI>
      <MDI key="STATISTICS_SKIPFACTORX">1</MDI>
      <MDI key="STATISTICS_SKIPFACTORY">1</MDI>
      <MDI key="STATISTICS_STDDEV">45.79563846417</MDI>
    </Metadata>
  </PAMRasterBand>
  <PAMRasterBand band="3">
    <Description>B</Description>
    <Histograms>
      <HistItem>
        <HistMin>-0.5</HistMin>
        <HistMax>235.5</HistMax>
        <BucketCount>236</BucketCount>
        <IncludeOutOfRange>1</IncludeOutOfRange>
        <Approximate>0</Approximate>
        <HistCounts>0|0|0|0|0|0|0|0|0|0|0|0|0|0|0|0|0|0|0|0|0|0|0|0|0|0|0|0|0|0|0|0|0|0|0|0|0|0|0|0|1|10|18|66|151|251|370|378|397|480|555|582|580|620|590|595|674|625|644|670|572|527|501|511|481|448|456|504|486|461|454|428|507|426|416|462|426|398|358|390|359|393|338|375|342|365|335|332|341|346|336|349|285|380|337|342|361|373|409|424|474|556|726|783|795|937|998|1098|1230|1254|1281|1230|1174|1218|1289|1397|1260|1118|1085|1017|959|845|808|735|691|658|570|542|460|501|470|485|559|497|510|500|534|535|538|481|535|528|565|527|565|524|530|477|493|468|539|494|446|525|497|493|447|444|499|500|452|405|403|392|438|504|390|322|334|304|294|328|264|283|289|321|335|364|335|466|398|504|462|493|456|468|354|265|233|259|251|246|233|204|164|131|125|118|120|107|175|158|162|190|176|225|270|313|435|530|627|917|1064|944|590|364|253|227|238|244|459|920|315|21|37|17|24|17|12|15|14|33|4|9|1|1</HistCounts>
      </HistItem>
    </Histograms>
    <Metadata>
      <MDI key="BandName">B</MDI>
      <MDI key="RepresentationType">ATHEMATIC</MDI>
      <MDI key="STATISTICS_COVARIANCES">2351.223959554112,2128.48113541406,2287.411231508765</MDI>
      <MDI key="STATISTICS_EXCLUDEDVALUES"></MDI>
      <MDI key="STATISTICS_MAXIMUM">235</MDI>
      <MDI key="STATISTICS_MEAN">126.7657696567</MDI>
      <MDI key="STATISTICS_MEDIAN">119.000000</MDI>
      <MDI key="STATISTICS_MINIMUM">40</MDI>
      <MDI key="STATISTICS_SKIPFACTORX">1</MDI>
      <MDI key="STATISTICS_SKIPFACTORY">1</MDI>
      <MDI key="STATISTICS_STDDEV">47.826888164596</MDI>
    </Metadata>
  </PAMRasterBand>
</PAMDataset>
